<?xml version="1.0" encoding="utf-8"?>
<TileSet Version="2" Name="BlueDragonVT">
	<TileSetConfig>
        <Compression>LZ4</Compression>
        <OneFilePerGTex>false</OneFilePerGTex>
        <BackfillPages>true</BackfillPages>
        <DeduplicateTiles>true</DeduplicateTiles>
        <ZeroBorders>false</ZeroBorders>
	</TileSetConfig>
	
	<Paths>
		<SourceTextures>Public\Hobgoblin\Assets\Textures</SourceTextures>
		<VirtualTextures>Public\Hobgoblin\Assets\VirtualTextures</VirtualTextures>
	</Paths>
	
	<Layers>
		<Layer Name="Albedo" Type="R8G8B8A8_SRGB" />
		<Layer Name="Normal" Type="X8Y8Z8W8" />
		<Layer Name="Physical" Type="X8Y8Z8W8" />
	</Layers>

	<Textures>
		<Texture Name="b6b33b1cc233463f8d64ff89b470da01">
			<Layer Name="Albedo" Source="Dragon_Blue_1_BM.DDS" />
			<Layer Name="Normal" Source="Dragon_Blue_1_NM.DDS" />
			<Layer Name="Physical" Source="Dragon_Blue_1_PM.DDS" />
		</Texture>
		<Texture Name="597a0940c84846ea8f93cc6bb740b7cc">
			<Layer Name="Albedo" Source="Dragon_Blue_2_BM.DDS" />
			<Layer Name="Normal" Source="Dragon_Blue_2_NM.DDS" />
			<Layer Name="Physical" Source="Dragon_Blue_2_PM.DDS" />
		</Texture>						
	</Textures>
</TileSet>
